fb_search
