Metadata-Version: 1.1
Name: facebook-image-search
Version: 0.0.3
Summary: Fetches public photos of any facebook id/username
Home-page: http://tusharmakkar08.github.io/Facebook_Graph_Search_Images/
Author: Tushar Makkar
Author-email: tusharmakkar08@gmail.com
License: MIT
Platform: any
Classifier: Programming Language :: Python :: 2.7
